rasqal/logger.py
rasqal/_native.pyi
rasqal/__init__.py
rasqal/simulators.py
rasqal/_native.cpython-310-x86_64-linux-gnu.so
rasqal/utils.py
rasqal/adaptors.py
rasqal/runtime.py
rasqal/routing.py
rasqal-0.1.7.dist-info/METADATA
rasqal-0.1.7.dist-info/RECORD
rasqal-0.1.7.dist-info/WHEEL
rasqal-0.1.7.dist-info/license_files/LICENSE
