Metadata-Version: 2.1
Name: rasqal
Version: 0.1.7
Classifier: License :: OSI Approved :: BSD License
Classifier: Development Status :: 3 - Alpha
Classifier: Intended Audience :: Developers
Classifier: Programming Language :: Python :: 3.10
Classifier: Programming Language :: Python
Classifier: Programming Language :: Rust
Classifier: Operating System :: MacOS
Classifier: Operating System :: Microsoft :: Windows
Classifier: Operating System :: POSIX :: Linux
Requires-Dist: qiskit==0.45.*,<1.0.0
Requires-Dist: qiskit-optimization>=0.4.0
Requires-Dist: qiskit-ignis>=0.7.0
Requires-Dist: qiskit-aer>=0.13.0
Requires-Dist: pytket>=1.31.0
License-File: LICENSE
Summary: A hybrid quantum-classical analysis/solving runtime.
Home-Page: 
Author: John Dumbell
Author-email: John Dumbell <john.dumbell42@gmail.com>
License: BSD-3-Clause
Requires-Python: >=3.10
Project-URL: Issues, https://github.com/oqc-community/rasqal/issues
Project-URL: Repository, https://github.com/oqc-community/rasqal.git
